MANIFEST.in
README.rst
dualtest.py
setup.py
tests.py
dualtest.egg-info/PKG-INFO
dualtest.egg-info/SOURCES.txt
dualtest.egg-info/dependency_links.txt
dualtest.egg-info/top_level.txt
testing/README
testing/setup.py
testing/srconlymodule.py
testing/testcases.py
testing/testmodule.c
testing/testmodule.py