Metadata-Version: 1.0
Name: dualtest
Version: 1.0
Summary: Easily test both Python and C versions of modules.
Home-page: UNKNOWN
Author: UNKNOWN
Author-email: UNKNOWN
License: UNKNOWN
Platform: UNKNOWN
